modelqueue/__init__.py
modelqueue-2.2.1.dist-info/LICENSE
modelqueue-2.2.1.dist-info/METADATA
modelqueue-2.2.1.dist-info/WHEEL
modelqueue-2.2.1.dist-info/top_level.txt
modelqueue-2.2.1.dist-info/RECORD
